pytest_celery/__init__.py
pytest_celery/api/__init__.py
pytest_celery/api/backend.py
pytest_celery/api/base.py
pytest_celery/api/broker.py
pytest_celery/api/container.py
pytest_celery/api/setup.py
pytest_celery/api/worker.py
pytest_celery/defaults.py
pytest_celery/fixtures/__init__.py
pytest_celery/fixtures/backend.py
pytest_celery/fixtures/broker.py
pytest_celery/fixtures/setup.py
pytest_celery/fixtures/worker.py
pytest_celery/plugin.py
pytest_celery/vendors/__init__.py
pytest_celery/vendors/localstack/__init__.py
pytest_celery/vendors/localstack/api.py
pytest_celery/vendors/localstack/container.py
pytest_celery/vendors/localstack/defaults.py
pytest_celery/vendors/localstack/fixtures.py
pytest_celery/vendors/memcached/__init__.py
pytest_celery/vendors/memcached/api.py
pytest_celery/vendors/memcached/container.py
pytest_celery/vendors/memcached/defaults.py
pytest_celery/vendors/memcached/fixtures.py
pytest_celery/vendors/rabbitmq/__init__.py
pytest_celery/vendors/rabbitmq/api.py
pytest_celery/vendors/rabbitmq/container.py
pytest_celery/vendors/rabbitmq/defaults.py
pytest_celery/vendors/rabbitmq/fixtures.py
pytest_celery/vendors/redis/__init__.py
pytest_celery/vendors/redis/backend/__init__.py
pytest_celery/vendors/redis/backend/api.py
pytest_celery/vendors/redis/backend/defaults.py
pytest_celery/vendors/redis/backend/fixtures.py
pytest_celery/vendors/redis/broker/__init__.py
pytest_celery/vendors/redis/broker/api.py
pytest_celery/vendors/redis/broker/defaults.py
pytest_celery/vendors/redis/broker/fixtures.py
pytest_celery/vendors/redis/container.py
pytest_celery/vendors/redis/defaults.py
pytest_celery/vendors/worker/Dockerfile
pytest_celery/vendors/worker/__init__.py
pytest_celery/vendors/worker/container.py
pytest_celery/vendors/worker/content/__init__.py
pytest_celery/vendors/worker/content/app.py
pytest_celery/vendors/worker/content/utils.py
pytest_celery/vendors/worker/defaults.py
pytest_celery/vendors/worker/fixtures.py
pytest_celery/vendors/worker/tasks.py
pytest_celery-1.2.1.dist-info/LICENSE
pytest_celery-1.2.1.dist-info/METADATA
pytest_celery-1.2.1.dist-info/WHEEL
pytest_celery-1.2.1.dist-info/entry_points.txt
pytest_celery-1.2.1.dist-info/RECORD
