Metadata-Version: 2.3
Name: pytest-celery
Version: 1.2.1
Summary: Pytest plugin for Celery
License: BSD-3-Clause
Keywords: pytest,celery
Author: Tomer Nosrati
Author-email: tomer.nosrati@gmail.com
Requires-Python: >=3.8,<4.0
Classifier: Development Status :: 5 - Production/Stable
Classifier: Framework :: Celery
Classifier: License :: OSI Approved :: BSD License
Classifier: Operating System :: OS Independent
Classifier: Programming Language :: Python
Classifier: Programming Language :: Python :: 3
Classifier: Programming Language :: Python :: 3.8
Classifier: Programming Language :: Python :: 3.9
Classifier: Programming Language :: Python :: 3.10
Classifier: Programming Language :: Python :: 3.11
Classifier: Programming Language :: Python :: 3.12
Classifier: Programming Language :: Python :: 3.13
Classifier: Programming Language :: Python :: 3 :: Only
Classifier: Programming Language :: Python :: Implementation :: CPython
Classifier: Topic :: Software Development :: Testing
Provides-Extra: all
Provides-Extra: memcached
Provides-Extra: redis
Provides-Extra: sqs
Requires-Dist: boto3 ; extra == "all" or extra == "sqs"
Requires-Dist: botocore ; extra == "all" or extra == "sqs"
Requires-Dist: celery
Requires-Dist: debugpy (>=1.8.12,<2.0.0)
Requires-Dist: docker (>=7.1.0,<8.0.0)
Requires-Dist: kombu
Requires-Dist: psutil (>=7.0.0)
Requires-Dist: pytest-docker-tools (>=3.1.3)
Requires-Dist: python-memcached ; extra == "all" or extra == "memcached"
Requires-Dist: redis ; extra == "all" or extra == "redis"
Requires-Dist: setuptools (>=60.0.0,<75.0.0) ; python_version == "3.8"
Requires-Dist: setuptools (>=75.8.0) ; python_version >= "3.9" and python_version < "4.0"
Requires-Dist: tenacity (>=9.0.0)
Requires-Dist: urllib3 (>=1.26.16,<2.0) ; extra == "all" or extra == "sqs"
Project-URL: Homepage, https://github.com/celery/pytest-celery
